LICENCE
lipilekhika/__init__.py
lipilekhika/_lipilekhika.cpython-314-aarch64-linux-gnu.so
lipilekhika/main.py
lipilekhika/types.py
lipilekhika/typing.py
lipilekhika-1.0.1.dist-info/METADATA
lipilekhika-1.0.1.dist-info/WHEEL
lipilekhika-1.0.1.dist-info/licenses/LICENCE
lipilekhika-1.0.1.dist-info/RECORD
