Metadata-Version: 2.4
Name: lipilekhika
Version: 1.0.1
License-File: LICENCE
Summary: A transliteration library for Indian Brahmic scripts
License-Expression: MIT
Requires-Python: >=3.10
